{
  "id": "ZPRAC_CDS_TABLE_ENTITIES",
  "title": "CDS Table Entities — Defining HANA database tables natively",
  "phase": 9,
  "phaseName": "Advanced Data Modeling",
  "category": "Advanced Data Modeling",
  "subcategory": "Tables & Projections",
  "language": "abap",
  "description": "CDS Table Entities — Defining HANA database tables natively. Key topics: define table entity is a new CDS DDL statement introduced in. Because the table is defined purely in CDS, the runtime object. Annotations control every aspect: @EndUserText.label provides.",
  "sections": [
    {
      "title": "Key Learning Points",
      "description": "<div class=\"text-slate-600 dark:text-slate-400 text-sm leading-relaxed\"><div class=\"flex items-start gap-2 mb-1.5\"><span class=\"text-brand-500 mt-0.5 shrink-0\">◆</span><span>define table entity is a new CDS DDL statement introduced in</span></div><div class=\"flex items-start gap-2 mb-1.5\"><span class=\"text-brand-500 mt-0.5 shrink-0\">◆</span><span>Because the table is defined purely in CDS, the runtime object</span></div><div class=\"flex items-start gap-2 mb-1.5\"><span class=\"text-brand-500 mt-0.5 shrink-0\">◆</span><span>Annotations control every aspect: @EndUserText.label provides</span></div><div class=\"flex items-start gap-2 mb-1.5\"><span class=\"text-brand-500 mt-0.5 shrink-0\">◆</span><span>Key fields, client handling, data elements, and built-in types</span></div><div class=\"flex items-start gap-2 mb-1.5\"><span class=\"text-brand-500 mt-0.5 shrink-0\">◆</span><span>@Semantics annotations for amount, quantity, currency, and</span></div><div class=\"flex items-start gap-2 mb-1.5\"><span class=\"text-brand-500 mt-0.5 shrink-0\">◆</span><span>Activation of a define table entity directly generates or</span></div></div>"
    },
    {
      "title": "CDS Source Code",
      "language": "abap",
      "codeBlock": "@EndUserText.label: 'Custom Audit Log Table Entity'\n@AbapCatalog.clientDependent: true\n@AbapCatalog.search.help: 'ZPRAC_AUDIT_LOG_SH'\ndefine table entity ZPRAC_AUDIT_LOG_TABLE {\n\n  @EndUserText.label: 'Client'\n  client                   : abap.clnt;\n\n  @EndUserText.label: 'Audit ID'\n  @AbapCatalog.foreignKey.keyType: #KEY\n  key audit_uuid           : sysuuid_x16;\n\n  @EndUserText.label: 'Timestamp'\n  @EndUserText.quickInfo: 'UTC Time Stamp of Audit Entry'\n  key audit_timestamp      : tzntstmpl;\n\n  @EndUserText.label: 'User Name'\n  user_name                : abap.uname;\n\n  @EndUserText.label: 'Action'\n  action                   : abap.char(40);\n\n  @EndUserText.label: 'Entity Name'\n  entity_name              : abap.char(60);\n\n  @EndUserText.label: 'Entity Key'\n  entity_key               : abap.string;\n\n  @EndUserText.label: 'Changed Value (Old)'\n  old_value                : abap.string;\n\n  @EndUserText.label: 'Changed Value (New)'\n  new_value                : abap.string;\n\n  @EndUserText.label: 'Change Amount'\n  @Semantics.amount.currencyCode: 'change_currency'\n  change_amount            : abap.curr(15,2);\n\n  @EndUserText.label: 'Change Currency'\n  @Semantics.currencyCode: true\n  change_currency          : abap.cuky;\n\n  @EndUserText.label: 'Change Quantity'\n  @Semantics.quantity.unitOfMeasure: 'change_unit'\n  change_quantity          : abap.quan(13,3);\n\n  @EndUserText.label: 'Change Unit'\n  @Semantics.unitOfMeasure: true\n  change_unit              : abap.unit(3);\n\n}"
    }
  ],
  "content": "<h2 id=\"section-ZPRAC_CDS_TABLE_ENTITIES-key-learning-points\">Key Learning Points</h2>\n<div class=\"text-slate-600 dark:text-slate-400 text-sm leading-relaxed\"><div class=\"flex items-start gap-2 mb-1.5\"><span class=\"text-brand-500 mt-0.5 shrink-0\">◆</span><span>define table entity is a new CDS DDL statement introduced in</span></div><div class=\"flex items-start gap-2 mb-1.5\"><span class=\"text-brand-500 mt-0.5 shrink-0\">◆</span><span>Because the table is defined purely in CDS, the runtime object</span></div><div class=\"flex items-start gap-2 mb-1.5\"><span class=\"text-brand-500 mt-0.5 shrink-0\">◆</span><span>Annotations control every aspect: @EndUserText.label provides</span></div><div class=\"flex items-start gap-2 mb-1.5\"><span class=\"text-brand-500 mt-0.5 shrink-0\">◆</span><span>Key fields, client handling, data elements, and built-in types</span></div><div class=\"flex items-start gap-2 mb-1.5\"><span class=\"text-brand-500 mt-0.5 shrink-0\">◆</span><span>@Semantics annotations for amount, quantity, currency, and</span></div><div class=\"flex items-start gap-2 mb-1.5\"><span class=\"text-brand-500 mt-0.5 shrink-0\">◆</span><span>Activation of a define table entity directly generates or</span></div></div>\n<h2 id=\"section-ZPRAC_CDS_TABLE_ENTITIES-cds-source-code\">CDS Source Code</h2>\n<pre><code class=\"language-abap\">@EndUserText.label: 'Custom Audit Log Table Entity'\n@AbapCatalog.clientDependent: true\n@AbapCatalog.search.help: 'ZPRAC_AUDIT_LOG_SH'\ndefine table entity ZPRAC_AUDIT_LOG_TABLE {\n\n  @EndUserText.label: 'Client'\n  client                   : abap.clnt;\n\n  @EndUserText.label: 'Audit ID'\n  @AbapCatalog.foreignKey.keyType: #KEY\n  key audit_uuid           : sysuuid_x16;\n\n  @EndUserText.label: 'Timestamp'\n  @EndUserText.quickInfo: 'UTC Time Stamp of Audit Entry'\n  key audit_timestamp      : tzntstmpl;\n\n  @EndUserText.label: 'User Name'\n  user_name                : abap.uname;\n\n  @EndUserText.label: 'Action'\n  action                   : abap.char(40);\n\n  @EndUserText.label: 'Entity Name'\n  entity_name              : abap.char(60);\n\n  @EndUserText.label: 'Entity Key'\n  entity_key               : abap.string;\n\n  @EndUserText.label: 'Changed Value (Old)'\n  old_value                : abap.string;\n\n  @EndUserText.label: 'Changed Value (New)'\n  new_value                : abap.string;\n\n  @EndUserText.label: 'Change Amount'\n  @Semantics.amount.currencyCode: 'change_currency'\n  change_amount            : abap.curr(15,2);\n\n  @EndUserText.label: 'Change Currency'\n  @Semantics.currencyCode: true\n  change_currency          : abap.cuky;\n\n  @EndUserText.label: 'Change Quantity'\n  @Semantics.quantity.unitOfMeasure: 'change_unit'\n  change_quantity          : abap.quan(13,3);\n\n  @EndUserText.label: 'Change Unit'\n  @Semantics.unitOfMeasure: true\n  change_unit              : abap.unit(3);\n\n}</code></pre>",
  "tags": [
    "cds-views"
  ],
  "details": "<p class=\"mb-2\">S/4HANA 2025 that creates a HANA database table directly from</p><p class=\"mb-2\">CDS source — no separate ABAP Dictionary (DDIC) table artifact</p><p class=\"mb-2\">is required as an intermediary.</p><p class=\"mb-2\">IS the HANA table; there is no DDIC table shell to maintain,</p><p class=\"mb-2\">reducing double-maintenance and transport complexity.</p><p class=\"mb-2\">the table description, @AbapCatalog.search.help attaches a</p><p class=\"mb-2\">search help, and @AbapCatalog.tableCategory can specify</p><p class=\"mb-2\">#TRANSPARENT or #CLUSTER semantics where relevant.</p><p class=\"mb-2\">are all supported; the client field (usually client = client;</p><p class=\"mb-2\">or using @AbapCatalog.clientDependent) mimics DDIC client</p><p class=\"mb-2\">behavior without a separate MANDT column definition.</p><p class=\"mb-2\">unit of measure work identically to CDS views, enabling the</p><p class=\"mb-2\">same analytical and transactional metadata natively on the</p><p class=\"mb-2\">table entity.</p><p class=\"mb-2\">updates the HANA table in the database; there is no separate</p><p class=\"mb-2\">activation of a DDIC table followed by a CDS view activation.</p><p class=\"mb-2\">Transport is handled via the CDS transport layer only.</p><p class=\"mb-2\">COMPARISON: Table Entity vs Traditional ABAP Dictionary Table</p><p class=\"mb-2\">Feature                    | define table entity        | Traditional DDIC Table</p><p class=\"mb-2\">---------------------------|----------------------------|---------------------------</p><p class=\"mb-2\">Artifact type              | CDS source (.asddls)       | DDIC table (.tab)</p><p class=\"mb-2\">Database object            | Direct HANA table          | Buffered via DDIC layer</p><p class=\"mb-2\">Separate DDIC step?        | No                         | Yes — maintain table in SE11</p><p class=\"mb-2\">Transport object           | CDS transport (DDL)        | DDIC transport (R3TR TABL)</p><p class=\"mb-2\">Annotation support         | Full CDS annotations       | Only DDIC field labels</p><p class=\"mb-2\">@Semantics.amount          | Yes                        | No (must be defined in view)</p><p class=\"mb-2\">Client handling            | @AbapCatalog.clientDependent| MANDT field + technical settings</p><p class=\"mb-2\">Search help attachment     | @AbapCatalog.search.help   | SE11 search help assignment</p><p class=\"mb-2\">Activation speed           | Single step (CDS → HANA)   | Two steps (DDIC + DB)</p><p class=\"mb-2\">RAP compatibility          | Native (CDS-managed)       | Requires CDS view wrapper</p><p class=\"mb-2\">SOURCE CODE: Custom Audit Log Table Entity</p>",
  "cdsViewName": "ZPRAC_CDS_TABLE_ENTITIES",
  "sqlViewName": "",
  "topic": "define table entity"
}